segno_quark.py
segno_quark-0.1.1.dist-info/DESCRIPTION.rst
segno_quark-0.1.1.dist-info/METADATA
segno_quark-0.1.1.dist-info/RECORD
segno_quark-0.1.1.dist-info/WHEEL
segno_quark-0.1.1.dist-info/entry_points.txt
segno_quark-0.1.1.dist-info/metadata.json
segno_quark-0.1.1.dist-info/top_level.txt
