Metadata-Version: 2.0
Name: segno-quark
Version: 0.1.1
Summary: Convert Segno's (Micro) QR Codes into more advanced SVG documents
Home-page: https://github.com/heuer/segno-quark/
Author: Lars Heuer
Author-email: heuer@semagia.com
License: BSD
Keywords: QR Code,Micro QR Code,ISO/IEC 18004,ISO/IEC 18004:2006(E)
Platform: any
Classifier: Development Status :: 4 - Beta
Classifier: Intended Audience :: Developers
Classifier: License :: OSI Approved :: BSD License
Classifier: Operating System :: OS Independent
Classifier: Programming Language :: Python
Classifier: Programming Language :: Python :: 2.6
Classifier: Programming Language :: Python :: 2.7
Classifier: Programming Language :: Python :: 3
Classifier: Topic :: Multimedia :: Graphics
Classifier: Topic :: Printing
Classifier: Topic :: Software Development :: Libraries :: Python Modules
Classifier: Topic :: Utilities
Requires-Dist: segno
